wulfric/__init__.py
wulfric/__main__.py
wulfric/_exceptions.py
wulfric/_kpoints_class.py
wulfric/_lepage.py
wulfric/_numerical.py
wulfric/_osfix.py
wulfric/_package_info.py
wulfric/_plotly_engine.py
wulfric/_spglib_interface.py
wulfric/_syntactic_sugar.py
wulfric/cell/__init__.py
wulfric/cell/_basic_manipulation.py
wulfric/cell/_niggli.py
wulfric/cell/_sc_examples.py
wulfric/cell/_voronoi.py
wulfric/constants/__init__.py
wulfric/constants/_atoms.py
wulfric/constants/_bravais_lattices.py
wulfric/constants/_hpkot_convention.py
wulfric/constants/_kpoints.py
wulfric/constants/_numerical.py
wulfric/constants/_sc_convention.py
wulfric/constants/_space_groups.py
wulfric/crystal/__init__.py
wulfric/crystal/_atoms.py
wulfric/crystal/_basic_manipulation.py
wulfric/crystal/_conventional.py
wulfric/crystal/_crystal_validation.py
wulfric/crystal/_hpkot_extended_bl_symbol.py
wulfric/crystal/_primitive.py
wulfric/crystal/_sc_variation.py
wulfric/crystal/_hpkot_examples/__init__.py
wulfric/crystal/_hpkot_examples/POSCAR-files/aP2/POSCAR_inversion
wulfric/crystal/_hpkot_examples/POSCAR-files/aP2/POSCAR_noinversion
wulfric/crystal/_hpkot_examples/POSCAR-files/aP3/POSCAR_inversion
wulfric/crystal/_hpkot_examples/POSCAR-files/aP3/POSCAR_noinversion
wulfric/crystal/_hpkot_examples/POSCAR-files/cF1/POSCAR_inversion
wulfric/crystal/_hpkot_examples/POSCAR-files/cF1/POSCAR_noinversion
wulfric/crystal/_hpkot_examples/POSCAR-files/cF2/POSCAR_inversion
wulfric/crystal/_hpkot_examples/POSCAR-files/cF2/POSCAR_noinversion
wulfric/crystal/_hpkot_examples/POSCAR-files/cI1/POSCAR_inversion
wulfric/crystal/_hpkot_examples/POSCAR-files/cI1/POSCAR_noinversion
wulfric/crystal/_hpkot_examples/POSCAR-files/cP1/POSCAR_inversion
wulfric/crystal/_hpkot_examples/POSCAR-files/cP1/POSCAR_noinversion
wulfric/crystal/_hpkot_examples/POSCAR-files/cP2/POSCAR_inversion
wulfric/crystal/_hpkot_examples/POSCAR-files/cP2/POSCAR_noinversion
wulfric/crystal/_hpkot_examples/POSCAR-files/hP1/POSCAR_inversion
wulfric-0.6.4.dist-info/licenses/LICENSE
wulfric-0.6.4.dist-info/licenses/LICENSE.template
wulfric-0.6.4.dist-info/METADATA
wulfric-0.6.4.dist-info/WHEEL
wulfric-0.6.4.dist-info/entry_points.txt
wulfric-0.6.4.dist-info/top_level.txt
wulfric-0.6.4.dist-info/RECORD
